[
    {
        "name": "Mekaron Helmet",
        "price": "500000"
    },
    {
        "name": "Blain Boots",
        "price": "500000"
    },
    {
        "name": "“Gynas Boots",
        "price": "500000"
    },
    {
        "name": "Lightning Card (4%)",
        "price": "5000000"
    },
    {
        "name": "Weeshian Gauntlets",
        "price": "500000"
    },
    {
        "name": "Gynas Gauntlets",
        "price": "500000"
    },
    {
        "name": "Stam Ring +3",
        "price": "500000"
    },
    {
        "name": "“Power Dice 10",
        "price": "10000000"
    },
    {
        "name": "Aken Boots",
        "price": "500000"
    },
    {
        "name": "Wees Boots +2",
        "price": "500000"
    }
]